VNP21A1D_002/VNP21A1D_002.py
VNP21A1D_002/VNP21A1D_granule.py
VNP21A1D_002/__init__.py
VNP21A1D_002/connection.py
VNP21A1D_002/constants.py
VNP21A1D_002/retrieve_granule.py
VNP21A1D_002/search_granules.py
VNP21A1D_002/version.py
vnp21a1d_002-1.2.1.dist-info/licenses/LICENSE
vnp21a1d_002-1.2.1.dist-info/METADATA
vnp21a1d_002-1.2.1.dist-info/WHEEL
vnp21a1d_002-1.2.1.dist-info/top_level.txt
vnp21a1d_002-1.2.1.dist-info/RECORD
